xcengine/__init__.py
xcengine/cli.py
xcengine/core.py
xcengine/parameters.py
xcengine/util.py
xcengine/wrapper.py
xcengine-0.1.0.dist-info/licenses/LICENSE
xcengine-0.1.0.dist-info/METADATA
xcengine-0.1.0.dist-info/WHEEL
xcengine-0.1.0.dist-info/entry_points.txt
xcengine-0.1.0.dist-info/top_level.txt
xcengine-0.1.0.dist-info/RECORD
