Metadata-Version: 2.4
Name: xcengine
Version: 0.1.0
Summary: Create OGC Earth Observation Application Packages from Jupyter notebooks
Author-email: Pontus Lurcock <pontus.lurcock@brockmann-consult.de>
License-Expression: MIT
Project-URL: Documentation, https://github.com/xcube-dev/xcengine/blob/main/README.md
Project-URL: Issues, https://github.com/xcube-dev/xcengine/issues
Project-URL: Changelog, https://github.com/xcube-dev/xcengine/blob/main/CHANGES.md
Project-URL: Repository, https://github.com/xcube-dev/xcengine
Project-URL: Homepage, https://github.com/xcube-dev/xcengine
Keywords: analysis ready data,data science,datacube,xarray,zarr
Classifier: Programming Language :: Python :: 3
Classifier: Operating System :: OS Independent
Classifier: Development Status :: 4 - Beta
Classifier: Topic :: Scientific/Engineering
Requires-Python: >=3.11
License-File: LICENSE
Requires-Dist: click
Requires-Dist: docker
Requires-Dist: ipython
Requires-Dist: nbconvert
Requires-Dist: nbformat
Requires-Dist: pystac
Requires-Dist: pyyaml
Requires-Dist: xarray
Requires-Dist: xcube-core
Provides-Extra: dev
Requires-Dist: pytest; extra == "dev"
Requires-Dist: pytest-cov; extra == "dev"
Requires-Dist: black; extra == "dev"
Requires-Dist: flake8; extra == "dev"
Provides-Extra: doc
Requires-Dist: mkdocs; extra == "doc"
Requires-Dist: mkdocs-material; extra == "doc"
Requires-Dist: mkdocstrings; extra == "doc"
Requires-Dist: mkdocstrings-python; extra == "doc"
Dynamic: license-file
